{"warnings": {"main": {"*": "Subscribe to the mediawiki-api-announce mailing list at <https://lists.wikimedia.org/postorius/lists/mediawiki-api-announce.lists.wikimedia.org/> for notice of API deprecations and breaking changes. Use [[Special:ApiFeatureUsage]] to see usage of deprecated features by your application."}, "parse": {"*": "\"prop=sections\" is deprecated since MediaWiki 1.46. Use \"prop=tocdata\" instead."}}, "parse": {"title": "Chico & the Gypsies", "pageid": 36570365, "sections": [{"toclevel": 1, "level": "2", "line": "Band members", "number": "1", "index": "1", "fromtitle": "Chico_&_the_Gypsies", "byteoffset": 1386, "anchor": "Band_members", "linkAnchor": "Band_members"}, {"toclevel": 1, "level": "2", "line": "Trivia", "number": "2", "index": "2", "fromtitle": "Chico_&_the_Gypsies", "byteoffset": 2113, "anchor": "Trivia", "linkAnchor": "Trivia"}, {"toclevel": 1, "level": "2", "line": "Discography", "number": "3", "index": "3", "fromtitle": "Chico_&_the_Gypsies", "byteoffset": 2275, "anchor": "Discography", "linkAnchor": "Discography"}, {"toclevel": 1, "level": "2", "line": "See also", "number": "4", "index": "4", "fromtitle": "Chico_&_the_Gypsies", "byteoffset": 5954, "anchor": "See_also", "linkAnchor": "See_also"}, {"toclevel": 1, "level": "2", "line": "References", "number": "5", "index": "5", "fromtitle": "Chico_&_the_Gypsies", "byteoffset": 6008, "anchor": "References", "linkAnchor": "References"}, {"toclevel": 1, "level": "2", "line": "External links", "number": "6", "index": "6", "fromtitle": "Chico_&_the_Gypsies", "byteoffset": 6036, "anchor": "External_links", "linkAnchor": "External_links"}], "showtoc": ""}}