{"continue": {"rvcontinue": "20200701170920|965493059", "continue": "||"}, "query": {"pages": {"6032766": {"pageid": 6032766, "ns": 0, "title": "York Guildhall", "revisions": [{"revid": 1308167449, "parentid": 1308165356, "user": "G-13114", "timestamp": "2025-08-27T22:02:02Z", "size": 7447, "comment": "Undid revision [[Special:Diff/1308165356|1308165356]] by [[Special:Contributions/92.22.138.255|92.22.138.255]] ([[User talk:92.22.138.255|talk]])"}, {"revid": 1308165356, "parentid": 1263840569, "user": "92.22.138.255", "anon": "", "timestamp": "2025-08-27T21:46:19Z", "size": 7380, "comment": ""}, {"revid": 1263840569, "parentid": 1235673137, "user": "JJMC89 bot III", "timestamp": "2024-12-18T23:25:10Z", "size": 7447, "comment": "Merging [[:Category:Government buildings completed in 1459]] to [[:Category:Buildings and structures completed in 1459]] and [[:Category:Government buildings completed in the 15th century]] per [[Wikipedia:Categories for discussion/Log/2024 December 10#Government buildings 1300-1700]]"}, {"revid": 1235673137, "parentid": 1232779084, "user": "The joy of all things", "timestamp": "2024-07-20T15:26:59Z", "size": 7379, "comment": "added non-breaking space"}, {"revid": 1232779084, "parentid": 1195583044, "user": "Stuart Newmanite", "timestamp": "2024-07-05T15:15:43Z", "size": 7374, "comment": "Added a category and rearranged the categories"}, {"revid": 1195583044, "parentid": 1193407130, "user": "I can smell the mistakes", "timestamp": "2024-01-14T12:47:58Z", "size": 7310, "comment": ""}, {"revid": 1193407130, "parentid": 1193405007, "user": "Dormskirk", "timestamp": "2024-01-03T17:55:19Z", "size": 7310, "comment": "tweak"}, {"revid": 1193405007, "parentid": 1159027936, "user": "144.32.240.81", "anon": "", "timestamp": "2024-01-03T17:44:29Z", "size": 7312, "comment": "Link to 3D Tour added"}, {"revid": 1159027936, "parentid": 1145670034, "user": "Chocolateediter", "timestamp": "2023-06-07T19:30:32Z", "size": 7182, "comment": "newer picture"}, {"revid": 1145670034, "parentid": 1145669918, "user": "Dormskirk", "timestamp": "2023-03-20T10:13:50Z", "size": 7151, "comment": "tweak"}, {"revid": 1145669918, "parentid": 1131277306, "user": "Dormskirk", "timestamp": "2023-03-20T10:12:54Z", "size": 7137, "comment": "expand"}, {"revid": 1131277306, "parentid": 1131276952, "user": "Dormskirk", "timestamp": "2023-01-03T11:30:23Z", "size": 7098, "comment": "/* History */ expand"}, {"revid": 1131276952, "parentid": 1131276651, "user": "Dormskirk", "timestamp": "2023-01-03T11:27:24Z", "size": 7042, "comment": "/* History */ tidy"}, {"revid": 1131276651, "parentid": 1131276543, "user": "Dormskirk", "timestamp": "2023-01-03T11:24:45Z", "size": 7032, "comment": "/* History */ tidy"}, {"revid": 1131276543, "parentid": 1131274526, "user": "Dormskirk", "timestamp": "2023-01-03T11:23:51Z", "size": 7024, "comment": "add reference and trim promotional material"}, {"revid": 1131274526, "parentid": 1131274448, "user": "144.32.238.96", "anon": "", "timestamp": "2023-01-03T11:07:09Z", "size": 7161, "comment": ""}, {"revid": 1131274448, "parentid": 1126357840, "user": "144.32.238.96", "anon": "", "timestamp": "2023-01-03T11:06:33Z", "size": 7153, "comment": ""}, {"revid": 1126357840, "parentid": 1116510875, "user": "Warofdreams", "timestamp": "2022-12-08T22:56:07Z", "size": 6617, "comment": "[[Category:St Helen's Square]]"}, {"revid": 1116510875, "parentid": 1116510301, "user": "Dormskirk", "timestamp": "2022-10-16T23:34:18Z", "size": 6586, "comment": "move image so it is more visable"}, {"revid": 1116510301, "parentid": 1112493818, "user": "Warofdreams", "timestamp": "2022-10-16T23:29:40Z", "size": 6587, "comment": "/* History */ + pic"}, {"revid": 1112493818, "parentid": 1084172882, "user": "GhostInTheMachine", "timestamp": "2022-09-26T16:12:39Z", "size": 6508, "comment": "Changing [[Wikipedia:Short description|short description]] from \"Municipal building in York, North Yorkshire, England\" to \"Grade I listed building in York, England\""}, {"revid": 1084172882, "parentid": 1075538593, "user": "Dormskirk", "timestamp": "2022-04-22T23:38:38Z", "size": 6520, "comment": "update"}, {"revid": 1075538593, "parentid": 1037100237, "user": "GhostInTheMachine", "timestamp": "2022-03-06T09:30:42Z", "size": 6514, "comment": "Adding local [[Wikipedia:Short description|short description]]: \"Grade I listed building in York, England\", overriding Wikidata description \"Rebuilt 15th-century city hall building in York, England\" ([[Wikipedia:Shortdesc helper|Shortdesc helper]])"}, {"revid": 1037100237, "parentid": 1002431876, "user": "Mndata2", "timestamp": "2021-08-04T14:34:38Z", "size": 6451, "comment": "/* History */Added commas"}, {"revid": 1002431876, "parentid": 1001750178, "user": "Monkbot", "timestamp": "2021-01-24T12:25:52Z", "size": 6395, "comment": "[[User:Monkbot/task 18|Task 18b (cosmetic)]]: eval 1 template: hyphenate params (1\u00d7);"}, {"revid": 1001750178, "parentid": 994388325, "user": "Monkbot", "timestamp": "2021-01-21T03:57:05Z", "size": 6394, "comment": "[[User:Monkbot/task 18|Task 18 (cosmetic)]]: eval 11 templates: hyphenate params (10\u00d7);"}, {"revid": 994388325, "parentid": 981319477, "user": "G-13114", "timestamp": "2020-12-15T13:26:34Z", "size": 6384, "comment": "/* External links */"}, {"revid": 981319477, "parentid": 980788941, "user": "Citation bot", "timestamp": "2020-10-01T16:07:21Z", "size": 6376, "comment": "Alter: url, title, pages. URLs might have been internationalized/anonymized. Add: archive-date, archive-url. Formatted [[WP:ENDASH|dashes]]. | You can [[WP:UCB|use this bot]] yourself. [[WP:DBUG|Report bugs here]]. | Suggested by AManWithNoPlan | All pages linked from cached copy of User:AManWithNoPlan/sandbox2 | via #UCB_webform_linked"}, {"revid": 980788941, "parentid": 973805746, "user": "Warofdreams", "timestamp": "2020-09-28T13:20:40Z", "size": 6100, "comment": "link"}, {"revid": 973805746, "parentid": 972416123, "user": "Dormskirk", "timestamp": "2020-08-19T09:04:12Z", "size": 6096, "comment": "/* External links */ cat"}, {"revid": 972416123, "parentid": 972416028, "user": "Dormskirk", "timestamp": "2020-08-11T23:31:02Z", "size": 6044, "comment": "/* History */ exp"}, {"revid": 972416028, "parentid": 972415962, "user": "Dormskirk", "timestamp": "2020-08-11T23:30:07Z", "size": 6040, "comment": "/* History */ exp"}, {"revid": 972415962, "parentid": 972415892, "user": "Dormskirk", "timestamp": "2020-08-11T23:29:26Z", "size": 6051, "comment": "/* History */ exp"}, {"revid": 972415892, "parentid": 972415680, "user": "Dormskirk", "timestamp": "2020-08-11T23:28:35Z", "size": 6059, "comment": "/* History */ exp"}, {"revid": 972415680, "parentid": 972415526, "user": "Dormskirk", "timestamp": "2020-08-11T23:26:03Z", "size": 5982, "comment": "/* History */ exp"}, {"revid": 972415526, "parentid": 972415363, "user": "Dormskirk", "timestamp": "2020-08-11T23:24:34Z", "size": 5960, "comment": "/* History */ ref"}, {"revid": 972415363, "parentid": 972414993, "user": "Dormskirk", "timestamp": "2020-08-11T23:22:52Z", "size": 5975, "comment": "/* History */ exp"}, {"revid": 972414993, "parentid": 972414845, "user": "Dormskirk", "timestamp": "2020-08-11T23:19:13Z", "size": 5690, "comment": "/* History */ exp"}, {"revid": 972414845, "parentid": 972413511, "user": "Dormskirk", "timestamp": "2020-08-11T23:17:51Z", "size": 5685, "comment": "expand and move reference inline"}, {"revid": 972413511, "parentid": 972413472, "user": "Dormskirk", "timestamp": "2020-08-11T23:08:49Z", "size": 5578, "comment": "/* History */ ref"}, {"revid": 972413472, "parentid": 972413062, "user": "Dormskirk", "timestamp": "2020-08-11T23:08:25Z", "size": 5578, "comment": "move in line"}, {"revid": 972413062, "parentid": 972412471, "user": "Dormskirk", "timestamp": "2020-08-11T23:05:14Z", "size": 5513, "comment": "/* History */ expand"}, {"revid": 972412471, "parentid": 965538297, "user": "Dormskirk", "timestamp": "2020-08-11T23:00:46Z", "size": 5111, "comment": "/* History */ tidy reference"}, {"revid": 965538297, "parentid": 965537746, "user": "Dormskirk", "timestamp": "2020-07-01T22:38:00Z", "size": 5356, "comment": "/* External links */ cat"}, {"revid": 965537746, "parentid": 965537557, "user": "Dormskirk", "timestamp": "2020-07-01T22:32:49Z", "size": 5312, "comment": "/* History */ exp"}, {"revid": 965537557, "parentid": 965519312, "user": "Dormskirk", "timestamp": "2020-07-01T22:31:17Z", "size": 5284, "comment": "/* History */ exp"}, {"revid": 965519312, "parentid": 965519263, "user": "Dormskirk", "timestamp": "2020-07-01T20:12:22Z", "size": 5277, "comment": "/* History */ exp"}, {"revid": 965519263, "parentid": 965519023, "user": "Dormskirk", "timestamp": "2020-07-01T20:12:01Z", "size": 5276, "comment": "/* History */ exp"}, {"revid": 965519023, "parentid": 965518716, "user": "Dormskirk", "timestamp": "2020-07-01T20:10:15Z", "size": 5258, "comment": "/* History */ exp"}, {"revid": 965518716, "parentid": 965493059, "user": "Dormskirk", "timestamp": "2020-07-01T20:07:44Z", "size": 5266, "comment": "/* History */ expand"}]}}}}