{"batchcomplete": "", "query": {"pages": {"48562538": {"pageid": 48562538, "ns": 0, "title": "Gerben Jorritsma", "templates": [{"ns": 10, "title": "Template:Birth date and age"}, {"ns": 10, "title": "Template:Br separated entries"}, {"ns": 10, "title": "Template:Bronze3"}, {"ns": 10, "title": "Template:Center"}, {"ns": 10, "title": "Template:Cite web"}, {"ns": 10, "title": "Template:Convinfobox"}, {"ns": 10, "title": "Template:Count"}, {"ns": 10, "title": "Template:Country data Australia"}, {"ns": 10, "title": "Template:Country data Canada"}, {"ns": 10, "title": "Template:Country data France"}, {"ns": 10, "title": "Template:Country data Germany"}, {"ns": 10, "title": "Template:Country data India"}, {"ns": 10, "title": "Template:Country data Italy"}, {"ns": 10, "title": "Template:Country data Japan"}, {"ns": 10, "title": "Template:Country data Netherlands"}, {"ns": 10, "title": "Template:Country data Poland"}, {"ns": 10, "title": "Template:Country data Russia"}, {"ns": 10, "title": "Template:Country data Spain"}, {"ns": 10, "title": "Template:Country data United States"}, {"ns": 10, "title": "Template:End"}, {"ns": 10, "title": "Template:If empty"}, {"ns": 10, "title": "Template:Infobox medal templates"}, {"ns": 10, "title": "Template:Infobox speed skater"}, {"ns": 10, "title": "Template:Infobox sportsperson"}, {"ns": 10, "title": "Template:Main other"}, {"ns": 10, "title": "Template:NED"}, {"ns": 10, "title": "Template:NLD"}, {"ns": 10, "title": "Template:Nowrap"}, {"ns": 10, "title": "Template:Pagetype"}, {"ns": 10, "title": "Template:PersonalRecordsBottom"}, {"ns": 10, "title": "Template:PersonalRecordsMiddle"}, {"ns": 10, "title": "Template:PersonalRecordsSport"}, {"ns": 10, "title": "Template:PersonalRecordsTop"}, {"ns": 10, "title": "Template:Plainlist/styles.css"}, {"ns": 10, "title": "Template:Pluralize from text"}, {"ns": 10, "title": "Template:Reflist"}, {"ns": 10, "title": "Template:Reflist/styles.css"}, {"ns": 10, "title": "Template:SDcat"}, {"ns": 10, "title": "Template:Short description"}, {"ns": 10, "title": "Template:Short description/lowercasecheck"}, {"ns": 10, "title": "Template:Silver2"}, {"ns": 10, "title": "Template:Sort"}, {"ns": 10, "title": "Template:Unbulleted list"}, {"ns": 10, "title": "Template:Wikidata image"}]}}}}