{"batchcomplete": "", "query": {"pages": {"61927264": {"pageid": 61927264, "ns": 0, "title": "Peggotty Beach", "extract": "Peggotty Beach is located in Scituate, Massachusetts. Peggotty is one of the five public beaches in Scituate and is half a mile long. Peggotty Beach is accessible through Peggotty Beach Road.\nIn 2016, a large storm flooded the beach. After this storm, the sand accumulated on the opposite side of the beach about 15 feet.\nIn 2019, Scituate received a grant to help protect Peggotty Beach shores."}}}}